sdi/__init__.py
sdi_python-1.0.0.dist-info/METADATA
sdi_python-1.0.0.dist-info/WHEEL
sdi_python-1.0.0.dist-info/top_level.txt
sdi_python-1.0.0.dist-info/RECORD
